example/__init__.py
example/voiceInterface.py
vosk/__init__.py
vosk/vosk_cffi.py
voskIntentVoiceConvertHanzi-0.3.32.dist-info/METADATA
voskIntentVoiceConvertHanzi-0.3.32.dist-info/WHEEL
voskIntentVoiceConvertHanzi-0.3.32.dist-info/top_level.txt
voskIntentVoiceConvertHanzi-0.3.32.dist-info/RECORD
