Metadata-Version: 2.1
Name: voskIntentVoiceConvertHanzi
Version: 0.3.32
Summary: Offline open source speech recognition API based on Kaldi and Vosk
Home-page: https://www.python.org/
Author: Alpha Cephei Inc
Author-email: contact@alphacephei.com
License: UNKNOWN
Platform: UNKNOWN
Classifier: Programming Language :: Python :: 3
Classifier: License :: OSI Approved :: Apache Software License
Classifier: Operating System :: Microsoft :: Windows
Classifier: Operating System :: POSIX :: Linux
Classifier: Operating System :: MacOS :: MacOS X
Classifier: Topic :: Software Development :: Libraries :: Python Modules
Requires-Python: >=3
Requires-Dist: cffi (>=1.0)
Requires-Dist: vosk
Requires-Dist: argparse
Requires-Dist: os
Requires-Dist: queue
Requires-Dist: sys
Requires-Dist: pyaudio
Requires-Dist: wave
Requires-Dist: json
Requires-Dist: keyboard
